kopen_data_builder/__init__.py
kopen_data_builder/registry.py
kopen_data_builder/cli/__init__.py
kopen_data_builder/cli/build_cmd.py
kopen_data_builder/cli/download_cmd.py
kopen_data_builder/cli/main.py
kopen_data_builder/cli/metadata_cmd.py
kopen_data_builder/cli/preprocess_cmd.py
kopen_data_builder/cli/split_cmd.py
kopen_data_builder/cli/upload_cmd.py
kopen_data_builder/core/__init__.py
kopen_data_builder/core/builder.py
kopen_data_builder/core/downloader.py
kopen_data_builder/core/enums.py
kopen_data_builder/core/metadata.py
kopen_data_builder/core/models.py
kopen_data_builder/core/preprocessing.py
kopen_data_builder/core/splitter.py
kopen_data_builder/core/uploader.py
kopen_data_builder/core/utils.py
kopen_data_builder/hooks/preprocessing.py
kopen_data_builder-0.1.0.dist-info/METADATA
kopen_data_builder-0.1.0.dist-info/WHEEL
kopen_data_builder-0.1.0.dist-info/entry_points.txt
kopen_data_builder-0.1.0.dist-info/licenses/LICENSE
kopen_data_builder-0.1.0.dist-info/RECORD
