Metadata-Version: 2.4
Name: kopen-data-builder
Version: 0.1.0
Summary: A universal CLI and SDK tool for transforming Korean public data into Hugging Face-compatible datasets.
Author-email: Yeongseon Choe <yeongseon.choe@gmail.com>
License: MIT
License-File: LICENSE
Keywords: cli,python,template,typer
Requires-Python: >=3.9
Requires-Dist: datasets
Requires-Dist: packaging
Requires-Dist: pandas
Requires-Dist: pydantic
Requires-Dist: requests
Requires-Dist: rich
Requires-Dist: scikit-learn
Requires-Dist: typer[all]
Provides-Extra: dev
Requires-Dist: black==24.3.0; extra == 'dev'
Requires-Dist: build; extra == 'dev'
Requires-Dist: hatch; extra == 'dev'
Requires-Dist: mkdocs; extra == 'dev'
Requires-Dist: mkdocs-material; extra == 'dev'
Requires-Dist: mkdocstrings[python]; extra == 'dev'
Requires-Dist: mypy==1.15.0; extra == 'dev'
Requires-Dist: pre-commit; extra == 'dev'
Requires-Dist: pytest; extra == 'dev'
Requires-Dist: pytest-cov; extra == 'dev'
Requires-Dist: pytest-mock; extra == 'dev'
Requires-Dist: ruff==0.1.11; extra == 'dev'
Requires-Dist: tox; extra == 'dev'
Requires-Dist: types-pyyaml; extra == 'dev'
Requires-Dist: types-requests; extra == 'dev'
